seismod1d/__init__.py
seismod1d/cmap.py
seismod1d/td.py
seismod1d/utils.py
seismod1d/wavelet.py
seismod1d/colormaps/grayscale_reverse.dat
seismod1d/colormaps/petrel_seismic_default.dat
seismod1d/colormaps/petrel_seismic_default_reverse.dat
seismod1d/model/SynthModel.py
seismod1d/model/__init__.py
seismod1d/model/export.py
seismod1d/model/lib.py
seismod1d/model/reflectivity.py
seismod1d/model/reflectivity_iso.py
seismod1d/model/reflectivity_vti.py
seismod1d/model/stack.py
seismod1d/model/synthetics.py
seismod1d/ray1d/__init__.py
seismod1d/ray1d/lib.py
seismod1d/ray1d/nmo.py
seismod1d/ray1d/ray1d.py
seismod1d/ray1d/trace.py
seismod1d/rockphysics/__init__.py
seismod1d/rockphysics/backus.py
seismod1d/rockphysics/conversions.py
seismod1d-0.3.6.dist-info/LICENSE.md
seismod1d-0.3.6.dist-info/METADATA
seismod1d-0.3.6.dist-info/WHEEL
seismod1d-0.3.6.dist-info/top_level.txt
seismod1d-0.3.6.dist-info/RECORD
