Metadata-Version: 2.1
Name: seismod1d
Version: 0.3.6
Summary: Create synthetic seismic 
Home-page: https://github.com/equinor/seismod1d
Author: Equinor ASA
Author-email: eidi@equinor.com
License: UNKNOWN
Platform: UNKNOWN
Classifier: Programming Language :: Python :: 3
Classifier: Operating System :: OS Independent
Requires-Python: >=3.9
License-File: LICENSE.md
Requires-Dist: numpy
Requires-Dist: pandas
Requires-Dist: matplotlib
Requires-Dist: scipy
Requires-Dist: lasio
Requires-Dist: segyio
